ntfy_evernote.py
ntfy_evernote-0.3.3.dist-info/LICENSE
ntfy_evernote-0.3.3.dist-info/WHEEL
ntfy_evernote-0.3.3.dist-info/METADATA
ntfy_evernote-0.3.3.dist-info/RECORD
