Metadata-Version: 2.1
Name: ntfy-evernote
Version: 0.3.3
Summary: Evernote backend for ntfy
Home-page: https://github.com/Cologler/ntfy-evernote-python
License: MIT
Author: Cologler
Author-email: skyoflw@gmail.com
Requires-Python: >=3.8,<4.0
Classifier: License :: OSI Approved :: MIT License
Classifier: Programming Language :: Python :: 3
Classifier: Programming Language :: Python :: 3.8
Requires-Dist: evernote3 (>=1.25.14,<2.0.0)
Requires-Dist: oauth2 (>=1.9.0,<2.0.0)
